airflow_ollama/__init__.py
airflow_ollama/operators/__init__.py
airflow_ollama/operators/ngrok_exposer_operator.py
airflow_ollama/operators/ollama_operator.py
airflow_ollama-0.11.0.dist-info/LICENSE
airflow_ollama-0.11.0.dist-info/METADATA
airflow_ollama-0.11.0.dist-info/WHEEL
airflow_ollama-0.11.0.dist-info/top_level.txt
airflow_ollama-0.11.0.dist-info/RECORD
