Metadata-Version: 2.1
Name: airflow-ollama
Version: 0.11.0
Summary: Airflow operator for managing Ollama and ngrok
Home-page: https://github.com/KarmaloopAI/Ollama-Airflow-Operator
Author: Abi Chatterjee
Author-email: abhishek.chatterjee@live.com
Keywords: airflow ollama ngrok operator
Classifier: Development Status :: 4 - Beta
Classifier: Intended Audience :: Developers
Classifier: License :: OSI Approved :: MIT License
Classifier: Operating System :: OS Independent
Classifier: Programming Language :: Python
Classifier: Programming Language :: Python :: 3
Classifier: Programming Language :: Python :: 3.7
Classifier: Programming Language :: Python :: 3.8
Classifier: Programming Language :: Python :: 3.9
Classifier: Programming Language :: Python :: 3.10
Classifier: Topic :: Software Development :: Libraries :: Python Modules
Requires-Python: >=3.7
License-File: LICENSE
Requires-Dist: apache-airflow >=2.0.0
Requires-Dist: requests >=2.25.0
Provides-Extra: dev
Requires-Dist: pytest >=6.0 ; extra == 'dev'
Requires-Dist: pytest-cov >=2.0 ; extra == 'dev'
Requires-Dist: flake8 >=3.9 ; extra == 'dev'
